pair_diff.py
pair_diff-1.2.0.dist-info/METADATA
pair_diff-1.2.0.dist-info/WHEEL
pair_diff-1.2.0.dist-info/entry_points.txt
pair_diff-1.2.0.dist-info/RECORD
